easy_use_tools/__init__.py
easy_use_tools/manage.py
easy_use_tools/core/__init__.py
easy_use_tools/core/description.py
easy_use_tools/utils/__init__.py
easy_use_tools/utils/common.py
easy_use_tools/utils/log.py
easy_use_tools/utils/common/__init__.py
easy_use_tools/utils/common/base.py
easy_use_tools/utils/common/gpu.py
easy_use_tools/utils/common/gui.py
easy_use_tools/utils/common/network.py
easy_use_tools/utils/common/system.py
easy_use_tools/utils/common/web_driver.py
easy_use_tools/utils/linux/__init__.py
easy_use_tools/utils/windows/__init__.py
easy_use_tools-1.0.6.dist-info/licenses/LICENSE
easy_use_tools-1.0.6.dist-info/METADATA
easy_use_tools-1.0.6.dist-info/WHEEL
easy_use_tools-1.0.6.dist-info/entry_points.txt
easy_use_tools-1.0.6.dist-info/top_level.txt
easy_use_tools-1.0.6.dist-info/RECORD
