Metadata-Version: 2.4
Name: easy_use_tools
Version: 1.0.6
Summary: An easy use tools package
Home-page: https://github.com/XXX
Author: yuanyang.li
Author-email: yuanyang.edison.li@gmail.com
Classifier: Programming Language :: Python :: 3
Classifier: Operating System :: OS Independent
Requires-Python: >=3.8
License-File: LICENSE
Requires-Dist: requests>=2.25.1
Requires-Dist: numpy>=1.19.5
Requires-Dist: shortuuid
Requires-Dist: py-cpuinfo
Requires-Dist: better_exceptions
Requires-Dist: wmi; sys_platform == "win32"
Dynamic: author
Dynamic: author-email
Dynamic: classifier
Dynamic: description
Dynamic: description-content-type
Dynamic: home-page
Dynamic: license-file
Dynamic: requires-dist
Dynamic: requires-python
Dynamic: summary
